dj_stripe_kando-1.0.0.dev3.dist-info/DESCRIPTION.rst
dj_stripe_kando-1.0.0.dev3.dist-info/METADATA
dj_stripe_kando-1.0.0.dev3.dist-info/RECORD
dj_stripe_kando-1.0.0.dev3.dist-info/WHEEL
dj_stripe_kando-1.0.0.dev3.dist-info/metadata.json
dj_stripe_kando-1.0.0.dev3.dist-info/top_level.txt
djstripe/__init__.py
djstripe/admin.py
djstripe/context_managers.py
djstripe/decorators.py
djstripe/event_handlers.py
djstripe/exceptions.py
djstripe/fields.py
djstripe/forms.py
djstripe/managers.py
djstripe/middleware.py
djstripe/mixins.py
djstripe/models.py
djstripe/settings.py
djstripe/signals.py
djstripe/stripe_objects.py
djstripe/sync.py
djstripe/urls.py
djstripe/utils.py
djstripe/views.py
djstripe/webhooks.py
djstripe/contrib/__init__.py
djstripe/contrib/rest_framework/__init__.py
djstripe/contrib/rest_framework/permissions.py
djstripe/contrib/rest_framework/serializers.py
djstripe/contrib/rest_framework/urls.py
djstripe/contrib/rest_framework/views.py
djstripe/management/__init__.py
djstripe/management/commands/__init__.py
djstripe/management/commands/djstripe_init_customers.py
djstripe/management/commands/djstripe_init_plans.py
djstripe/management/commands/djstripe_sync_customers.py
djstripe/migrations/0001_initial.py
djstripe/migrations/0001_squashed_0007_for_custom_subscriber_model.py
djstripe/migrations/0002_auto_20150122_2000.py
djstripe/migrations/0003_auto_20150128_0800.py
djstripe/migrations/0004_auto_20150427_1609.py
djstripe/migrations/0005_charge_captured.py
djstripe/migrations/0006_auto_20150602_1934.py
djstripe/migrations/0007_auto_20150625_1243.py
djstripe/migrations/0008_auto_20150806_1641.py
djstripe/migrations/0009_auto_20160501_1838.py
djstripe/migrations/0010_splitting_up_adds_from_alters.py
djstripe/migrations/0011_charge_captured_update.py
djstripe/migrations/0012_model_sync.py
djstripe/migrations/0013_sync_cleanup.py
djstripe/migrations/0014_auto_20160625_1851.py
djstripe/migrations/0015_upcoming_invoices.py
djstripe/migrations/0016_stripe_id_255_length.py
djstripe/migrations/0017_set_null_on_delete.py
djstripe/migrations/0018_field_docs.py
djstripe/migrations/0019_purge_on_subscriber_delete.py
djstripe/migrations/0020_auto_20161229_0041.py
