Metadata-Version: 2.0
Name: dj-stripe-kando
Version: 1.0.0.dev3
Summary: Django + Stripe Made Easy
Home-page: https://github.com/kavdev/dj-stripe/
Author: Alexander Kavanaugh
Author-email: alex@kavdev.io
License: License :: OSI Approved :: BSD License
Keywords: stripe django
Platform: UNKNOWN
Classifier: Development Status :: 4 - Beta
Classifier: Environment :: Web Environment
Classifier: Framework :: Django
Classifier: Framework :: Django :: 1.8
Classifier: Intended Audience :: Developers
Classifier: License :: OSI Approved :: BSD License
Classifier: Natural Language :: English
Classifier: Programming Language :: Python :: 2
Classifier: Programming Language :: Python :: 2.7
Classifier: Programming Language :: Python :: 3
Classifier: Programming Language :: Python :: 3.4
Classifier: Programming Language :: Python :: 3.5
Requires-Dist: django (!=1.9,>=1.8)
Requires-Dist: django-braces (>=1.9.0)
Requires-Dist: django-model-utils (>=2.5.2)
Requires-Dist: django-polymorphic (>=1.0)
Requires-Dist: jsonfield (>=1.0.3)
Requires-Dist: pytz (>=2016.6.1)
Requires-Dist: stripe (>=1.41.1)
Requires-Dist: tqdm (>=4.8.4)
Requires-Dist: python-doc-inherit (~=0.3.0)
Requires-Dist: mock-django (~=0.6.10)
